etrnpy/__init__.py
etrnpy/format.py
etrnpy/log.py
etrnpy/logging_log.py
etrnpy/changes/__init__.py
etrnpy/changes/additions.py
etrnpy/changes/elimintations.py
etrnpy/changes/versioning.py
etrnpy/config/__init__.py
etrnpy/config/accounts.py
etrnpy/land/__init__.py
etrnpy/land/land_functions.py
etrnpy/loop/__init__.py
etrnpy/loop/loop.py
example_pkg/__init__.py
etrnpy-0.0.4.dist-info/LICENSE
etrnpy-0.0.4.dist-info/METADATA
etrnpy-0.0.4.dist-info/WHEEL
etrnpy-0.0.4.dist-info/top_level.txt
etrnpy-0.0.4.dist-info/RECORD
