Metadata-Version: 2.1
Name: etrnpy
Version: 0.0.4
Summary: etrnpy: ETRN's Python Library
Home-page: https://github.com/pypa/sampleproject
Author: Kirsten Luzik
Author-email: kluzik@equitransmidstream.com
License: UNKNOWN
Project-URL: Bug Tracker, https://github.com/pypa/sampleproject/issues
Platform: UNKNOWN
Classifier: Programming Language :: Python :: 3
Classifier: License :: OSI Approved :: MIT License
Classifier: Operating System :: OS Independent
Requires-Python: >=2.7
